meteocat_api/Manager.py
meteocat_api/Observation.py
meteocat_api/Site.py
meteocat_api/Timestep.py
meteocat_api/__init__.py
meteocat_api/_version.py
meteocat_api/exceptions.py
meteocat_api/profile.py
meteocat_api-0.0.3.dist-info/LICENSE
meteocat_api-0.0.3.dist-info/METADATA
meteocat_api-0.0.3.dist-info/WHEEL
meteocat_api-0.0.3.dist-info/top_level.txt
meteocat_api-0.0.3.dist-info/RECORD
