Metadata-Version: 2.1
Name: meteocat-api
Version: 0.0.3
Summary: Meteocat API to retrieve Meteocat data
Home-page: UNKNOWN
Author: Alvaro Rodriguez
Author-email: alvaro.rdrgz.ramos@gmail.com
License: UNKNOWN
Platform: UNKNOWN
Classifier: Programming Language :: Python :: 3
Classifier: License :: OSI Approved :: MIT License
Classifier: Operating System :: OS Independent
